streamlit_audio_queue_player/__init__.py
streamlit_audio_queue_player/frontend/build/asset-manifest.json
streamlit_audio_queue_player/frontend/build/index.html
streamlit_audio_queue_player/frontend/build/static/js/main.cede29f8.js
streamlit_audio_queue_player/frontend/build/static/js/main.cede29f8.js.LICENSE.txt
streamlit_audio_queue_player/frontend/build/static/js/main.cede29f8.js.map
streamlit_audio_queue_player-0.1.2.dist-info/LICENSE
streamlit_audio_queue_player-0.1.2.dist-info/METADATA
streamlit_audio_queue_player-0.1.2.dist-info/WHEEL
streamlit_audio_queue_player-0.1.2.dist-info/top_level.txt
streamlit_audio_queue_player-0.1.2.dist-info/RECORD
