Metadata-Version: 2.2
Name: streamlit-audio-queue-player
Version: 0.1.2
Summary: A Streamlit component for sequential audio playback with an internal queue.
Home-page: https://github.com/neon-izm/streamlit-audio-queue-player
Author: neon izm
Author-email: jj.y0sh1da@gmail.com
Classifier: Programming Language :: Python :: 3
Classifier: License :: OSI Approved :: MIT License
Classifier: Operating System :: OS Independent
Requires-Python: >=3.6
License-File: LICENSE
Requires-Dist: streamlit>=1.0.0
Dynamic: author
Dynamic: author-email
Dynamic: classifier
Dynamic: description
Dynamic: description-content-type
Dynamic: home-page
Dynamic: requires-dist
Dynamic: requires-python
Dynamic: summary
